tempread/__init__.py
tempread/main.py
tempread-0.1.0.dist-info/METADATA
tempread-0.1.0.dist-info/WHEEL
tempread-0.1.0.dist-info/entry_points.txt
tempread-0.1.0.dist-info/top_level.txt
tempread-0.1.0.dist-info/RECORD
