Metadata-Version: 2.4
Name: tempread
Version: 0.1.0
Summary: CLI-tool to display CPU-temperatures
Author-email: Leon Krämer <leon.kraemer.dev@gmail.com>
Requires-Python: >=3.7
Requires-Dist: psutil
